ReadingFilledForm/.___init__.py
ReadingFilledForm/._clsAlignTemplates.py
ReadingFilledForm/._clsConfig.py
ReadingFilledForm/._clsL.py
ReadingFilledForm/._clsReadForm.py
ReadingFilledForm/__init__.py
ReadingFilledForm/clsAlignTemplates.py
ReadingFilledForm/clsConfig.py
ReadingFilledForm/clsL.py
ReadingFilledForm/clsReadForm.py
ReadingFilledForm/log/readingForm.log
readingfilledform-0.0.7.dist-info/METADATA
readingfilledform-0.0.7.dist-info/WHEEL
readingfilledform-0.0.7.dist-info/RECORD
