Metadata-Version: 2.1
Name: ReadingFilledForm
Version: 0.0.7
Summary: This is the main calling python script that will invoke the class to initiate the reading capability & display text from a formatted forms.
Project-URL: Homepage, https://github.com/SatyakiDe2019/ScannedCopyDataExtraction
Project-URL: Bug Tracker, https://github.com/SatyakiDe2019/ScannedCopyDataExtraction/issues
Author-email: Satyaki De <satyakide.us@gmail.com>
License: Copyright 2022 @ Satyaki De
Classifier: License :: OSI Approved :: MIT License
Classifier: Operating System :: OS Independent
Classifier: Programming Language :: Python :: 3
Requires-Python: >=3.7
